Metadata-Version: 2.1
Name: easylogging
Version: 1.2.0
Summary: Simple Python logging lib
Home-page: https://github.com/AI35/easylogging
Author: ALI B OTHMAN
Author-email: alosh.othman55@gmail.com
License: LICENSE.txt
Project-URL: Bug Reports, https://github.com/AI35/easylogging/issues
Project-URL: Source, https://github.com/AI35/easylogging
Keywords: logging logger log
Platform: UNKNOWN
Requires-Python: >=3
